Workbook
Name EURTAKA: [1]Rates!$B$1
Name EURTAKA: Rates!$B$1

Sheet  Landed Cost
A2: Engine Capacity | B2: Price of Vehicle C.I.F Dhaka (EUR) | C2: Duty Percentage (%) | D2: Customs Duty | E2: Customs Clearing Misc. Charges & Insurance-Local (3%) | F2: Local Transportation | G2: Landed Cost in EURO | H2: Landed Cost in BDTK | I2: Margin % | J2: Ex Showroom in BDTK | K2: Ex Showroom in EURO | L2: Margin in EURO | M2: Margin in BDT | S2: PROFIT IN COGS (%) | T2: Margin | U2: %
A3: A4 2.0 TFSI | B3: 52000 | C3: 2.1717368 | D3: =(B3*C3) -> 112930.31 | E3: =(B3+D3)*3% -> 4947.9094 | F3: 750 | G3: =B3+D3+E3+F3 -> 170628.22 | H3: =G3*Rates!$B$4 -> 15015284 | I3: 0.1 | J3: =H3/(100%-I3) -> 16683648 | K3: =J3/Rates!$B$4 -> 189586.91 | L3: =K3-G3 -> 18958.691 | M3: =J3-H3 -> 1668364.8 | O3: =H3/90 -> 166836.48 | S3: =#REF!+#REF!*10% -> #REF! | T3: =S3-#REF! -> #REF! | U3: =T3/#REF! -> #REF! | V3: =#REF!/#REF! -> #REF!
A4: A6 1.8TFSI | B4: 55 | C4: 2.1717 | D4: =(B4*C4) -> 119.4435 | E4: =(B4+D4)*3% -> 5.233305 | F4: 750 | G4: =B4+D4+E4+F4 -> 929.67681 | H4: =G4*Rates!$B$4 -> 81811.559 | I4: 0.15 | J4: =H4/(100%-I4) -> 96248.893 | K4: =J4/Rates!$B$4 -> 1093.7374 | L4: =K4-G4 -> 164.06061 | M4: =J4-H4 -> 14437.334 | O4: =O3*100 -> 16683648 | S4: =#REF!+#REF!*10% -> #REF! | T4: =S4-#REF! -> #REF! | U4: =T4/#REF! -> #REF! | V4: =#REF!/#REF! -> #REF!
A5: Q3 2.0 TFSI | B5: 100 | C5: 2.1717 | D5: =(B5*C5) -> 217.17 | E5: =(B5+D5)*3% -> 9.5151 | F5: 750 | G5: =B5+D5+E5+F5 -> 1076.6851 | H5: =G5*Rates!$B$4 -> 94748.289 | I5: 0.15 | J5: =H5/(100%-I5) -> 111468.58 | K5: =J5/Rates!$B$4 -> 1266.6884 | L5: =K5-G5 -> 190.00325 | M5: =J5-H5 -> 16720.286 | S5: =#REF!+#REF!*10% -> #REF! | T5: =S5-#REF! -> #REF! | U5: =T5/#REF! -> #REF! | V5: =#REF!/#REF! -> #REF!
A6: Q7 2.0 TFSI | B6: 45000 | C6: 2.1717 | D6: =(B6*C6) -> 97726.5 | E6: =(B6+D6)*3% -> 4281.795 | F6: 750 | G6: =B6+D6+E6+F6 -> 147758.3 | H6: =G6*Rates!$B$4 -> 13002730 | I6: 0.15 | J6: =H6/(100%-I6) -> 15297329 | K6: =J6/Rates!$B$4 -> 173833.29 | L6: =K6-G6 -> 26074.993 | M6: =J6-H6 -> 2294599.4 | O6: =H3/90 -> 166836.48 | S6: =#REF!+#REF!*12% -> #REF! | T6: =S6-#REF! -> #REF! | U6: =T6/#REF! -> #REF! | V6: =#REF!/#REF! -> #REF!
O7: =O6*100 -> 16683648
A10: Base Value | B10: Amount in BDT | C10: Customs Duty(CD) (25%) | D10: Regulatory Duty(RD) (5%) | E10: Supplementary Duty(SD) (100%) | F10: VAT (15%) | G10: Advance Income Tax(AIT) (5%) | H10: Amount in BDT+CD+RD+SD*26.67% | I10: Amount in BDT+CD+RD+SD | J10: Advance Trade Vat(ATV) (4%) | K10: Total Duty in BDT
A11: 52000 | B11: =SUM(A11*88.72) -> 4613440 | C11: =SUM(B11*25%) -> 1153360 | D11: =SUM(B11*5%) -> 230672 | E11: =SUM((B11+C11+D11)*100%) -> 5997472 | F11: =SUM((B11+C11+D11+E11)*15%) -> 1799241.6 | G11: =SUM(B11*5%) -> 230672 | H11: =SUM((B11+C11+D11+E11)*26.67%) -> 3199051.6 | I11: =SUM(H11+B11+C11+D11+E11) -> 15193996 | J11: =SUM(I11*4%) -> 607759.82 | K11: =SUM(C11+D11+E11+F11+G11+J11) -> 10019177
K12: =K11/B11*100 -> 217.17368
J14: =(H3/(100-10)) -> 166836.48

Sheet Rates
A4: Euro to TAKA | B4: 88
